[{
  "_id": 1,
  "idCliente": 1,
  "idProducto": 1,
  "idCategoria": 1,
  "fecha": "2024-12-24T12:00:00",
  "comentario": "¡Excelente calidad y muy rápido!",
  "puntuacion": 5
},
{
  "_id": 2,
  "idCliente": 2,
  "idProducto": 2,
  "idCategoria": 1,
  "fecha": "2024-12-20T14:00:00",
  "comentario": "Muy buen celular, pero un poco caro.",
  "puntuacion": 4
},
{
  "_id": 3,
  "idCliente": 3,
  "idProducto": 3,
  "idCategoria": 1,
  "fecha": "2024-12-15T09:30:00",
  "comentario": "Excelente relación calidad-precio.",
  "puntuacion": 5
},
{
  "_id": 4,
  "idCliente": 4,
  "idProducto": 4,
  "idCategoria": 1,
  "fecha": "2024-12-10T11:00:00",
  "comentario": "Cumple perfectamente con lo que promete.",
  "puntuacion": 4
},
{
  "_id": 5,
  "idCliente": 5,
  "idProducto": 5,
  "idCategoria": 1,
  "fecha": "2024-12-08T16:45:00",
  "comentario": "Buena batería y diseño cómodo.",
  "puntuacion": 5
},
{
  "_id": 6,
  "idCliente": 6,
  "idProducto": 11,
  "idCategoria": 2,
  "fecha": "2024-12-24T12:00:00",
  "comentario": "Muy práctico y fácil de usar.",
  "puntuacion": 5
},
{
  "_id": 7,
  "idCliente": 7,
  "idProducto": 12,
  "idCategoria": 2,
  "fecha": "2024-12-20T14:00:00",
  "comentario": "Cocina muy rápido y tiene buen diseño.",
  "puntuacion": 4
},
{
  "_id": 8,
  "idCliente": 8,
  "idProducto": 13,
  "idCategoria": 2,
  "fecha": "2024-12-15T09:30:00",
  "comentario": "Compacto y funcional, excelente compra.",
  "puntuacion": 5
},
{
  "_id": 9,
  "idCliente": 9,
  "idProducto": 14,
  "idCategoria": 2,
  "fecha": "2024-12-10T11:00:00",
  "comentario": "Perfecto para espacios pequeños.",
  "puntuacion": 4
},
{
  "_id": 10,
  "idCliente": 10,
  "idProducto": 15,
  "idCategoria": 2,
  "fecha": "2024-12-08T16:45:00",
  "comentario": "Funciona muy bien para mi cocina.",
  "puntuacion": 5
},
{
  "_id": 11,
  "idCliente": 11,
  "idProducto": 20,
  "idCategoria": 3,
  "fecha": "2024-12-24T12:00:00",
  "comentario": "Potente y eficiente, limpia todo a fondo.",
  "puntuacion": 5
},
{
  "_id": 12,
  "idCliente": 1,
  "idProducto": 21,
  "idCategoria": 3,
  "fecha": "2024-12-20T14:00:00",
  "comentario": "Compacta y con buena potencia.",
  "puntuacion": 4
},
{
  "_id": 13,
  "idCliente": 2,
  "idProducto": 22,
  "idCategoria": 3,
  "fecha": "2024-12-15T09:30:00",
  "comentario": "Muy práctica y fácil de usar.",
  "puntuacion": 5
},
{
  "_id": 14,
  "idCliente": 3,
  "idProducto": 23,
  "idCategoria": 3,
  "fecha": "2024-12-10T11:00:00",
  "comentario": "El mejor producto que he comprado.",
  "puntuacion": 5
},
{
  "_id": 15,
  "idCliente": 4,
  "idProducto": 24,
  "idCategoria": 3,
  "fecha": "2024-12-08T16:45:00",
  "comentario": "Buen diseño y excelente potencia.",
  "puntuacion": 4
},
{
  "_id": 16,
  "idCliente": 5,
  "idProducto": 30,
  "idCategoria": 4,
  "fecha": "2024-12-24T12:00:00",
  "comentario": "Muy eficiente y fácil de manejar.",
  "puntuacion": 5
},
{
  "_id": 17,
  "idCliente": 6,
  "idProducto": 31,
  "idCategoria": 4,
  "fecha": "2024-12-20T14:00:00",
  "comentario": "Perfecta para mi jardín pequeño.",
  "puntuacion": 4
},
{
  "_id": 18,
  "idCliente": 7,
  "idProducto": 32,
  "idCategoria": 4,
  "fecha": "2024-12-15T09:30:00",
  "comentario": "Cumple con lo esperado.",
  "puntuacion": 5
},
{
  "_id": 19,
  "idCliente": 8,
  "idProducto": 33,
  "idCategoria": 4,
  "fecha": "2024-12-10T11:00:00",
  "comentario": "Muy potente y con excelente duración.",
  "puntuacion": 5
},
{
  "_id": 20,
  "idCliente": 9,
  "idProducto": 34,
  "idCategoria": 4,
  "fecha": "2024-12-08T16:45:00",
  "comentario": "Ideal para el mantenimiento del jardín.",
  "puntuacion": 4
}]